Workbook

Sheet Sheet1
A1: S.No | B1: Category | C1: Product | D1: Quantity | E1: Price (₹)
A2: 1 | B2: Dairy | C2: Aavin Milk | D2: 500 ml | E2: 25
A3: 2 | B3: Dairy | C3: Aavin Curd | D3: 500 g | E3: 35
A4: 3 | B4: Dairy | C4: Amul Butter | D4: 100 g | E4: 60
A5: 4 | B5: Dairy | C5: Milky Mist Paneer | D5: 200 g | E5: 110
A6: 5 | B6: Dairy | C6: Amul Cheese | D6: 200 g | E6: 145
A7: 6 | B7: Toothpaste | C7: Colgate Active Salt Max Fresh | D7: 100 g | E7: 82
A8: 7 | B8: Toothpaste | C8: Pepsodent Germicheck | D8: 100 g | E8: 70
A9: 8 | B9: Soap | C9: Hamam | D9: 100 g | E9: 38
A10: 9 | B10: Soap | C10: Medimix | D10: 100 g | E10: 40
A11: 10 | B11: Soap | C11: Lifebuoy | D11: 100 g | E11: 35
A12: 11 | B12: Shampoo | C12: Clinic Plus | D12: 180 ml | E12: 110
A13: 12 | B13: Shampoo | C13: Sunsilk | D13: 180 ml | E13: 110
... A41: 40 | B41: Vegetables & Fruits | C41: Apple | D41: 1 kg | E41: 180

Sheet Products
A1: Product_ID | B1: Category | C1: Product_Name | D1: Pack_Size | E1: Unit_Price | F1: Barcode | G1: Scan_Code | H1: QR_URL | I1: Image_URL | J1: QR_Preview | K1: Stock_Qty | L1: Reorder_Level | M1: Is_Active | N1: Updated_At
A2: PRD001 | B2: Dairy | C2: Aavin Milk | D2: 500 ml | E2: 25 | G2: SM-PRD001 | H2: =IF(G2="","","https://quickchart.io/qr?text="&ENCODEURL(G2)) -> https://quickchart.io/qr?text=SM-PRD001 | J2: =HYPERLINK(H2,"Open QR") -> Open QR | K2: 100 | L2: 10 | M2: TRUE | N2: 2026-10-03T17:44:00+05:30
A3: PRD002 | B3: Dairy | C3: Aavin Curd | D3: 500 g | E3: 35 | G3: SM-PRD002 | H3: =IF(G3="","","https://quickchart.io/qr?text="&ENCODEURL(G3)) -> https://quickchart.io/qr?text=SM-PRD002 | J3: =HYPERLINK(H3,"Open QR") -> Open QR | K3: 100 | L3: 10 | M3: TRUE | N3: 2026-10-03T17:44:00+05:30
A4: PRD003 | B4: Dairy | C4: Amul Butter | D4: 100 g | E4: 60 | G4: SM-PRD003 | H4: =IF(G4="","","https://quickchart.io/qr?text="&ENCODEURL(G4)) -> https://quickchart.io/qr?text=SM-PRD003 | J4: =HYPERLINK(H4,"Open QR") -> Open QR | K4: 100 | L4: 10 | M4: TRUE | N4: 2026-10-03T17:44:00+05:30
A5: PRD004 | B5: Dairy | C5: Milky Mist Paneer | D5: 200 g | E5: 110 | G5: SM-PRD004 | H5: =IF(G5="","","https://quickchart.io/qr?text="&ENCODEURL(G5)) -> https://quickchart.io/qr?text=SM-PRD004 | J5: =HYPERLINK(H5,"Open QR") -> Open QR | K5: 100 | L5: 10 | M5: TRUE | N5: 2026-10-03T17:44:00+05:30
A6: PRD005 | B6: Dairy | C6: Amul Cheese | D6: 200 g | E6: 145 | G6: SM-PRD005 | H6: =IF(G6="","","https://quickchart.io/qr?text="&ENCODEURL(G6)) -> https://quickchart.io/qr?text=SM-PRD005 | J6: =HYPERLINK(H6,"Open QR") -> Open QR | K6: 100 | L6: 10 | M6: TRUE | N6: 2026-10-03T17:44:00+05:30
A7: PRD006 | B7: Toothpaste | C7: Colgate Active Salt Max Fresh | D7: 100 g | E7: 82 | G7: SM-PRD006 | H7: =IF(G7="","","https://quickchart.io/qr?text="&ENCODEURL(G7)) -> https://quickchart.io/qr?text=SM-PRD006 | J7: =HYPERLINK(H7,"Open QR") -> Open QR | K7: 100 | L7: 10 | M7: TRUE | N7: 2026-10-03T17:44:00+05:30
A8: PRD007 | B8: Toothpaste | C8: Pepsodent Germicheck | D8: 100 g | E8: 70 | G8: SM-PRD007 | H8: =IF(G8="","","https://quickchart.io/qr?text="&ENCODEURL(G8)) -> https://quickchart.io/qr?text=SM-PRD007 | J8: =HYPERLINK(H8,"Open QR") -> Open QR | K8: 100 | L8: 10 | M8: TRUE | N8: 2026-10-03T17:44:00+05:30
A9: PRD008 | B9: Soap | C9: Hamam | D9: 100 g | E9: 38 | G9: SM-PRD008 | H9: =IF(G9="","","https://quickchart.io/qr?text="&ENCODEURL(G9)) -> https://quickchart.io/qr?text=SM-PRD008 | J9: =HYPERLINK(H9,"Open QR") -> Open QR | K9: 100 | L9: 10 | M9: TRUE | N9: 2026-10-03T17:44:00+05:30
A10: PRD009 | B10: Soap | C10: Medimix | D10: 100 g | E10: 40 | G10: SM-PRD009 | H10: =IF(G10="","","https://quickchart.io/qr?text="&ENCODEURL(G10)) -> https://quickchart.io/qr?text=SM-PRD009 | J10: =HYPERLINK(H10,"Open QR") -> Open QR | K10: 100 | L10: 10 | M10: TRUE | N10: 2026-10-03T17:44:00+05:30
A11: PRD010 | B11: Soap | C11: Lifebuoy | D11: 100 g | E11: 35 | G11: SM-PRD010 | H11: =IF(G11="","","https://quickchart.io/qr?text="&ENCODEURL(G11)) -> https://quickchart.io/qr?text=SM-PRD010 | J11: =HYPERLINK(H11,"Open QR") -> Open QR | K11: 100 | L11: 10 | M11: TRUE | N11: 2026-10-03T17:44:00+05:30
A12: PRD011 | B12: Shampoo | C12: Clinic Plus | D12: 180 ml | E12: 110 | G12: SM-PRD011 | H12: =IF(G12="","","https://quickchart.io/qr?text="&ENCODEURL(G12)) -> https://quickchart.io/qr?text=SM-PRD011 | J12: =HYPERLINK(H12,"Open QR") -> Open QR | K12: 100 | L12: 10 | M12: TRUE | N12: 2026-10-03T17:44:00+05:30
A13: PRD012 | B13: Shampoo | C13: Sunsilk | D13: 180 ml | E13: 110 | G13: SM-PRD012 | H13: =IF(G13="","","https://quickchart.io/qr?text="&ENCODEURL(G13)) -> https://quickchart.io/qr?text=SM-PRD012 | J13: =HYPERLINK(H13,"Open QR") -> Open QR | K13: 100 | L13: 10 | M13: TRUE | N13: 2026-10-03T17:44:00+05:30
... A41: PRD040 | B41: Vegetables & Fruits | C41: Apple | D41: 1 kg | E41: 180 | G41: SM-PRD040 | H41: =IF(G41="","","https://quickchart.io/qr?text="&ENCODEURL(G41)) -> https://quickchart.io/qr?text=SM-PRD040 | J41: =HYPERLINK(H41,"Open QR") -> Open QR | K41: 100 | L41: 10 | M41: TRUE | N41: 2026-10-03T17:44:00+05:30
M42: FALSE
M43: FALSE
M44: FALSE
M45: FALSE
M46: FALSE
M47: FALSE
M48: FALSE
M49: FALSE
M50: FALSE
M51: FALSE
M52: FALSE
M53: FALSE
... M1000: FALSE

Sheet Trolleys
A1: Trolley_ID | B1: QR_Payload | C1: QR_URL | D1: QR_Preview | E1: Status | F1: Current_Session_ID | G1: Current_User_ID | H1: Last_Checkout_At | I1: Last_Returned_At | J1: Last_Updated_At | K1: Notes
A2: TROLLEY-01 | B2: SM-TROLLEY-01 | C2: =IF(B2="","","https://quickchart.io/qr?text="&ENCODEURL(B2)) -> https://quickchart.io/qr?text=SM-TROLLEY-01 | D2: =HYPERLINK(C2,"Open QR") -> Open QR | E2: AVAILABLE | J2: 2026-10-03T17:44:00+05:30 | K2: Ready for customer check-in
A3: TROLLEY-02 | B3: SM-TROLLEY-02 | C3: =IF(B3="","","https://quickchart.io/qr?text="&ENCODEURL(B3)) -> https://quickchart.io/qr?text=SM-TROLLEY-02 | D3: =HYPERLINK(C3,"Open QR") -> Open QR | E3: AVAILABLE | J3: 2026-10-03T17:44:00+05:30 | K3: Ready for customer check-in
A4: TROLLEY-03 | B4: SM-TROLLEY-03 | C4: =IF(B4="","","https://quickchart.io/qr?text="&ENCODEURL(B4)) -> https://quickchart.io/qr?text=SM-TROLLEY-03 | D4: =HYPERLINK(C4,"Open QR") -> Open QR | E4: AVAILABLE | J4: 2026-10-03T17:44:00+05:30 | K4: Ready for customer check-in
A5: TROLLEY-04 | B5: SM-TROLLEY-04 | C5: =IF(B5="","","https://quickchart.io/qr?text="&ENCODEURL(B5)) -> https://quickchart.io/qr?text=SM-TROLLEY-04 | D5: =HYPERLINK(C5,"Open QR") -> Open QR | E5: AVAILABLE | J5: 2026-10-03T17:44:00+05:30 | K5: Ready for customer check-in

Sheet Users
A1: User_ID | B1: Name | C1: Phone | D1: Email | E1: Role | F1: Status | G1: Created_At
A2: USER-DEMO-001 | B2: Demo Customer | E2: CUSTOMER | F2: ACTIVE | G2: 2026-10-03T17:44:00+05:30
A3: ADMIN-001 | B3: Smart Market Admin | E3: ADMIN | F3: ACTIVE | G3: 2026-10-03T17:44:00+05:30
A4: DISPATCH-001 | B4: Dispatch Staff | E4: DISPATCH | F4: ACTIVE | G4: 2026-10-03T17:44:00+05:30

Sheet Sessions
A1: Session_ID | B1: User_ID | C1: Trolley_ID | D1: Check_In_At | E1: Status | F1: Check_Out_At | G1: Order_ID | H1: Last_Activity_At | I1: Version | J1: Close_Reason

Sheet CartItems
A1: Cart_Item_ID | B1: Session_ID | C1: Product_ID | D1: Quantity | E1: Unit_Price | F1: Line_Total | G1: Added_At | H1: Updated_At | I1: Status

Sheet Orders
A1: Order_ID | B1: Session_ID | C1: Trolley_ID | D1: User_ID | E1: Subtotal | F1: Discount | G1: Tax | H1: Grand_Total | I1: Payment_Method | J1: Payment_Status | K1: Order_Status | L1: Created_At | M1: Paid_At | N1: Dispatch_At | O1: Completed_At | P1: Version

Sheet Payments
A1: Payment_ID | B1: Order_ID | C1: Method | D1: Amount | E1: Status | F1: Reference | G1: Collected_By | H1: Created_At | I1: Confirmed_At

Sheet DispatchLog
A1: Dispatch_ID | B1: Order_ID | C1: Trolley_ID | D1: Payment_Check | E1: Items_Check | F1: Approved_By | G1: Dispatch_Status | H1: Created_At | I1: Returned_At | J1: Return_Verified_By

Sheet AuditLog
A1: Event_ID | B1: Timestamp | C1: Request_ID | D1: Actor_ID | E1: Actor_Role | F1: Entity_Type | G1: Entity_ID | H1: Action | I1: Result | J1: Details

Sheet Settings
A1: Key | B1: Value | C1: Notes
A2: STORE_NAME | B2: Smart Market | C2: Application display name
A3: ENV | B3: TEST | C3: Change to PROD only after testing
A4: APP_VERSION | B4: MVP-1.0 | C4: Backend schema version
A5: CURRENCY | B5: INR | C5: Indian Rupee
A6: TAX_PERCENT | B6: 0 | C6: Applied at checkout
A7: UPI_ID | B7: UPDATE_ME@upi | C7: Replace before live UPI testing
A8: MAX_ITEM_QTY | B8: 20 | C8: Maximum quantity of one product in a session
A9: SESSION_TIMEOUT_MIN | B9: 120 | C9: Use for stale-session cleanup
A10: TROLLEY_COUNT | B10: 4 | C10: Configured physical trolleys
A11: CASH_ENABLED | B11: TRUE | C11: Cash requires admin confirmation
A12: UPI_ENABLED | B12: TRUE | C12: UPI payment option
A13: QR_ENABLED | B13: TRUE | C13: QR payment option
A14: REQUIRE_DISPATCH_PAYMENT | B14: TRUE | C14: Never dispatch unpaid order
A15: REQUIRE_RETURN_SCAN | B15: TRUE | C15: Trolley release requires return scan
A16: QR_PROVIDER | B16: https://quickchart.io/qr | C16: Used for test QR images
A17: APPS_SCRIPT_WEBAPP_URL | C17: Fill after deploying Apps Script
A18: ADMIN_NOTIFICATION_EMAIL | C18: Optional
A19: DATA_MODEL | B19: SESSION_CART_ORDER_PAYMENT_DISPATCH | C19: Do not merge these tables

Sheet Admin_Dashboard
A1: SMART MARKET CONTROL CENTER
A2: Live operational summary
A3: Metric | B3: Value | D3: Trolley | E3: Status | F3: Session | G3: User | H3: Last Updated
A4: Available Trolleys | B4: =COUNTIF(Trolleys!E2:E100,"AVAILABLE") -> 4 | D4: TROLLEY-01 | E4: =Trolleys!E2 -> AVAILABLE | F4: =Trolleys!F2 | G4: =Trolleys!G2 | H4: =Trolleys!J2 -> 2026-10-03T17:44:00+05:30
A5: In Use | B5: =COUNTIF(Trolleys!E2:E100,"IN_USE") -> 0 | D5: TROLLEY-02 | E5: =Trolleys!E3 -> AVAILABLE | F5: =Trolleys!F3 | G5: =Trolleys!G3 | H5: =Trolleys!J3 -> 2026-10-03T17:44:00+05:30
A6: Payment Pending | B6: =COUNTIF(Orders!J2:J100,"PENDING")+COUNTIF(Orders!J2:J100,"UNPAID") -> 0 | D6: TROLLEY-03 | E6: =Trolleys!E4 -> AVAILABLE | F6: =Trolleys!F4 | G6: =Trolleys!G4 | H6: =Trolleys!J4 -> 2026-10-03T17:44:00+05:30
A7: Ready for Dispatch | B7: =COUNTIF(Orders!K2:K100,"READY_FOR_DISPATCH") -> 0 | D7: TROLLEY-04 | E7: =Trolleys!E5 -> AVAILABLE | F7: =Trolleys!F5 | G7: =Trolleys!G5 | H7: =Trolleys!J5 -> 2026-10-03T17:44:00+05:30
A8: Completed Orders | B8: =COUNTIF(Orders!K2:K100,"COMPLETED") -> 0
A9: Open Sessions | B9: =COUNTIF(Sessions!E2:E100,"ACTIVE")+COUNTIF(Sessions!E2:E100,"CHECKOUT") -> 0
A10: Paid Revenue | B10: =SUMIF(Orders!J2:J100,"PAID",Orders!H2:H100) -> 0
A12: Operational rule | B12: Value
A13: Dispatch requires PAID | B13: {=_xlfn.XLOOKUP("REQUIRE_DISPATCH_PAYMENT",Settings!A:A,Settings!B:B,"TRUE")} -> TRUE
A14: Return scan required | B14: {=_xlfn.XLOOKUP("REQUIRE_RETURN_SCAN",Settings!A:A,Settings!B:B,"TRUE")} -> TRUE

Sheet AppSheet_Config
A1: Component | B1: Table | C1: Key_Column | D1: Label_Column | E1: Suggested_View | F1: Filter_or_Expression | G1: Notes
A2: Data | B2: Products | C2: Product_ID | D2: Product_Name | E2: Deck / Gallery | F2: [Is_Active]=TRUE | G2: Barcode/QR scan target = Scan_Code or Barcode
A3: Data | B3: Trolleys | C3: Trolley_ID | D3: Trolley_ID | E3: Deck | F3: TRUE | G3: Customer should only see AVAILABLE or own trolley
A4: Data | B4: Users | C4: User_ID | D4: Name | E4: Table | F4: [Status]="ACTIVE" | G4: Role controls admin/dispatch views
A5: Data | B5: Sessions | C5: Session_ID | D5: Session_ID | E5: Detail | F5: [User_ID]=LOOKUP(USEREMAIL(),"Users","Email","User_ID") | G5: One active session per user
A6: Data | B6: CartItems | C6: Cart_Item_ID | D6: Product_ID | E6: Table | F6: [Status]="ACTIVE" | G6: Quantity editable only before checkout
A7: Data | B7: Orders | C7: Order_ID | D7: Order_ID | E7: Detail | F7: TRUE | G7: Server recalculates totals
A8: Data | B8: Payments | C8: Payment_ID | D8: Order_ID | E8: Table | F8: TRUE | G8: Cash must be admin-confirmed
A9: Data | B9: DispatchLog | C9: Dispatch_ID | D9: Trolley_ID | E9: Table | F9: TRUE | G9: Dispatch and return audit
A10: Data | B10: AuditLog | C10: Event_ID | D10: Action | E10: Table | F10: FALSE | G10: Admin-only read-only
A11: UX | B11: Customer Home | E11: Dashboard | G11: Check In → Scan Item → Cart → Pay → Exit
A12: UX | B12: Admin Home | E12: Dashboard | G12: Trolley live status + pending payments + dispatch
A13: UX | B13: Dispatch | E13: Scanner | G13: Scan trolley; show red block when unpaid
A14: Action | B14: CHECK_IN | E14: Webhook / Script | F14: registerTrolleyScan(userId,trolleyId,requestId) | G14: Use scanner value from trolley QR
A15: Action | B15: ADD_ITEM | E15: Webhook / Script | F15: addProductScan(sessionId,scanCode,1,requestId) | G15: Repeated scan increments quantity
A16: Action | B16: REMOVE_ITEM | E16: Webhook / Script | F16: removeProduct(sessionId,productId,1,requestId) | G16: Cannot edit after checkout
A17: Action | B17: CHECKOUT | E17: Webhook / Script | F17: checkoutSession(sessionId,paymentMethod,requestId) | G17: Empty cart blocked
A18: Action | B18: CONFIRM_PAYMENT | E18: Admin only | F18: confirmPayment(orderId,method,amount,reference,adminId,requestId) | G18: Idempotent payment confirmation
A19: Action | B19: DISPATCH | E19: Dispatch only | F19: confirmDispatch(trolleyId,staffId,requestId) | G19: Requires paid order
A20: Action | B20: RETURN | E20: Dispatch only | F20: returnTrolley(trolleyId,staffId,requestId) | G20: Releases trolley to AVAILABLE
A21: Security | B21: Admin views | F21: IN(USEREMAIL(),SELECT(Users[Email],[Role]="ADMIN")) | G21: Prefer sign-in required
A22: Security | B22: Dispatch views | F22: IN(USEREMAIL(),SELECT(Users[Email],[Role]="DISPATCH")) | G22: No product/admin editing
A23: Scanner | B23: Product | E23: Scan | F23: Barcode + QR | G23: Use Barcode when populated, otherwise custom Scan_Code QR
A24: Scanner | B24: Trolley | E24: Scan | F24: QR_Payload | G24: Four permanent trolley QR codes

Sheet Test_Cases
A1: Test_ID | B1: Scenario | C1: Precondition | D1: Action | E1: Expected_Result | F1: Severity | G1: Status | H1: Actual_Result
A2: TC001 | B2: Check-in available trolley | C2: USER-DEMO-001 + TROLLEY-01 | D2: Call registerTrolleyScan | E2: Session created; trolley IN_USE | F2: Critical | G2: Not Run
A3: TC002 | B3: Two users claim same trolley | C3: Second user scans TROLLEY-01 while in use | D3: Call registerTrolleyScan | E3: Blocked; original session unchanged | F3: Critical | G3: Not Run
A4: TC003 | B4: One user claims second trolley | C4: User already has ACTIVE session | D4: Scan another trolley | E4: Blocked | F4: High | G4: Not Run
A5: TC004 | B5: Invalid trolley QR | C5: Unknown trolley code | D5: Check-in | E5: Blocked with TROLLEY_NOT_FOUND | F5: High | G5: Not Run
A6: TC005 | B6: Blocked trolley | C6: Set trolley status BLOCKED | D6: Check-in | E6: Blocked | F6: High | G6: Not Run
A7: TC006 | B7: Valid product scan | C7: Active session + SM-PRD001 | D7: Add item | E7: Cart line qty=1, price snapshot stored | F7: Critical | G7: Not Run
A8: TC007 | B8: Repeat product scan | C8: Same product scanned twice | D8: Add item again | E8: Same cart line qty increments; no duplicate active line | F8: High | G8: Not Run
A9: TC008 | B9: Max item quantity | C9: Qty reaches MAX_ITEM_QTY | D9: Scan again | E9: Blocked | F9: Medium | G9: Not Run
A10: TC009 | B10: Remove one quantity | C10: Qty > 1 | D10: Remove product | E10: Qty decremented | F10: High | G10: Not Run
A11: TC010 | B11: Remove last quantity | C11: Qty = 1 | D11: Remove product | E11: Line status REMOVED / no active quantity | F11: High | G11: Not Run
A12: TC011 | B12: Checkout empty cart | C12: Active session no items | D12: Checkout | E12: Blocked | F12: Critical | G12: Not Run
A13: TC012 | B13: Valid checkout | C13: Cart has items | D13: Checkout Cash | E13: Order created; payment PENDING; trolley PAYMENT_PENDING | F13: Critical | G13: Not Run
... A31: TC030 | B31: Audit coverage | C31: Run full happy path | D31: Inspect AuditLog | E31: Every state-changing step logged with result | F31: High | G31: Not Run
